README.md
setup.py
src/__init__.py
src/computeKd.py
src/compute_jarzynski.py
src/jarzynski.egg-info/PKG-INFO
src/jarzynski.egg-info/SOURCES.txt
src/jarzynski.egg-info/dependency_links.txt
src/jarzynski.egg-info/top_level.txt