Metadata-Version: 2.1
Name: jarzynski
Version: 1.0.4
Summary: A computational tool to compute PMF and Kd from non-equilibrium simulation
Home-page: https://github.com/groponp/Jarzynski
Download-URL: https://github.com/groponp/Jarzynski/tarball/1.0.3
Author: Ropón-Palacios G.
Author-email: groponp@gmail.com
License: GPLv3
Keywords: non-equilibrium md,jarzynski,PMF,Kd
